metronome_pulse_postgres_psycopg3/__init__.py
metronome_pulse_postgres_psycopg3/connector.py
metronome_pulse_postgres_psycopg3/sql_builder.py
metronome_pulse_postgres_psycopg3-0.1.0.dist-info/METADATA
metronome_pulse_postgres_psycopg3-0.1.0.dist-info/WHEEL
metronome_pulse_postgres_psycopg3-0.1.0.dist-info/RECORD
