Metadata-Version: 2.4
Name: metronome-pulse-postgres-psycopg3
Version: 0.1.0
Summary: PostgreSQL DataPulse connector using psycopg3
Project-URL: Homepage, https://github.com/datametronome/metronome-pulse-postgres-psycopg3
Project-URL: Repository, https://github.com/datametronome/metronome-pulse-postgres-psycopg3
Project-URL: Documentation, https://datametronome.dev/docs/pulse-postgres-psycopg3
Project-URL: Issues, https://github.com/datametronome/metronome-pulse-postgres-psycopg3/issues
Author-email: DataMetronome Team <team@datametronome.dev>
License: MIT
Classifier: Development Status :: 3 - Alpha
Classifier: Intended Audience :: Developers
Classifier: License :: OSI Approved :: MIT License
Classifier: Programming Language :: Python :: 3
Classifier: Programming Language :: Python :: 3.9
Classifier: Programming Language :: Python :: 3.10
Classifier: Programming Language :: Python :: 3.11
Classifier: Programming Language :: Python :: 3.12
Classifier: Programming Language :: Python :: 3.13
Classifier: Topic :: Database
Classifier: Topic :: Database :: Front-Ends
Classifier: Topic :: Software Development :: Libraries :: Python Modules
Requires-Python: >=3.9
Requires-Dist: metronome-pulse-core>=0.1.0
Requires-Dist: psycopg[pool]>=3.1.0
